{"version":1,"resource":"file:///home/berend/Documents/dev/MindstormRobot/Cargo.toml","entries":[{"id":"B58H.toml","timestamp":1680449357947},{"id":"Vitw.toml","timestamp":1680450024067},{"id":"QwmI.toml","timestamp":1680528793809},{"id":"U4rI.toml","timestamp":1680528898003},{"id":"ilMp.toml","timestamp":1680529300230},{"id":"lzLz.toml","timestamp":1680944472815},{"id":"37R9.toml","timestamp":1680944484491},{"id":"nHAZ.toml","timestamp":1680944501840},{"id":"NpZd.toml","timestamp":1680944515816},{"id":"m41v.toml","timestamp":1680944532645},{"id":"NUqV.toml","timestamp":1680944795985},{"id":"plyX.toml","source":"undoRedo.source","timestamp":1680944851615}]}